async_amqp/__init__.py
async_amqp/channel.py
async_amqp/constants.py
async_amqp/envelope.py
async_amqp/exceptions.py
async_amqp/frame.py
async_amqp/future.py
async_amqp/properties.py
async_amqp/protocol.py
async_amqp-0.5.5.dist-info/AUTHORS.rst
async_amqp-0.5.5.dist-info/LICENSE
async_amqp-0.5.5.dist-info/METADATA
async_amqp-0.5.5.dist-info/WHEEL
async_amqp-0.5.5.dist-info/top_level.txt
async_amqp-0.5.5.dist-info/RECORD
