Metadata-Version: 2.1
Name: async-amqp
Version: 0.5.5
Summary: AMQP implementation using anyio
Home-page: https://github.com/python-trio/async_amqp
Author: Matthias Urlichs
Author-email: matthias@urlichs.de
License: BSD
Keywords: asyncio,amqp,rabbitmq,aio,trio
Platform: all
Classifier: Development Status :: 4 - Beta
Classifier: Intended Audience :: Developers
Classifier: License :: OSI Approved :: BSD License
Classifier: Operating System :: OS Independent
Classifier: Programming Language :: Python
Classifier: Programming Language :: Python :: 3
Classifier: Programming Language :: Python :: 3.6
Classifier: Programming Language :: Python :: 3.7
Classifier: Programming Language :: Python :: 3.8
Classifier: Programming Language :: Python :: 3.9
Classifier: Framework :: Trio
License-File: LICENSE
License-File: AUTHORS.rst
Requires-Dist: anyio (>=3)
Requires-Dist: pamqp (<4,>=3)
